LICENSE.txt
MANIFEST.in
README.md
requirements.txt
setup.cfg
setup.py
setup_prerequisites.py
version.txt
kudu/__init__.pxd
kudu/__init__.py
kudu/client.cpp
kudu/client.pxd
kudu/client.pyx
kudu/compat.py
kudu/config.pxi
kudu/config.pxi.in
kudu/errors.cpp
kudu/errors.pxd
kudu/errors.pyx
kudu/libkudu_client.pxd
kudu/schema.cpp
kudu/schema.pxd
kudu/schema.pyx
kudu/util.py
kudu/version.py
kudu_python.egg-info/PKG-INFO
kudu_python.egg-info/SOURCES.txt
kudu_python.egg-info/dependency_links.txt
kudu_python.egg-info/requires.txt
kudu_python.egg-info/top_level.txt